notifiercraft/__init__.py
notifiercraft/asyncio/__init__.py
notifiercraft/asyncio/async_client.py
notifiercraft/client.py
notifiercraft/error/__init__.py
notifiercraft/error/unsupported_sender_type.py
notifiercraft/sender/__init__.py
notifiercraft/sender/email.py
notifiercraft/sender/telegram.py
notifier_craft-0.1.0.dist-info/LICENSE
notifier_craft-0.1.0.dist-info/METADATA
notifier_craft-0.1.0.dist-info/WHEEL
notifier_craft-0.1.0.dist-info/RECORD
