Metadata-Version: 2.1
Name: notifier-craft
Version: 0.1.0
Summary: Async/sync library for sending notifications
Home-page: https://github.com/marakhd/notifier-craft
License: MIT
Keywords: notify, notifycraft, notify-craft, notifications, marakhd
Author: marakhd
Author-email: marakin09@mail.ru
Requires-Python: >=3.12,<4.0
Classifier: License :: OSI Approved :: MIT License
Classifier: Programming Language :: Python :: 3
Classifier: Programming Language :: Python :: 3.12
Requires-Dist: aiogram (>=3.10.0,<4.0.0)
Requires-Dist: pytelegrambotapi (>=4.21.0,<5.0.0)
Project-URL: Repository, https://github.com/marakhd/notifier-craft
